df_compare/__init__.py
df_compare/compare_files.py
df_compare/core.py
df_compare/pytest_kit.py
df_compare/version.py
df_compare-0.0.1.dist-info/LICENSE.txt
df_compare-0.0.1.dist-info/METADATA
df_compare-0.0.1.dist-info/WHEEL
df_compare-0.0.1.dist-info/entry_points.txt
df_compare-0.0.1.dist-info/top_level.txt
df_compare-0.0.1.dist-info/RECORD
