Metadata-Version: 2.1
Name: df-compare
Version: 0.0.1
Summary: APF Engine: Distributed Python Workflow configuration and execution platform
Home-page: UNKNOWN
Maintainer: AGT
Maintainer-email: casey.clements@gmail.com
License: BSD
Platform: MacOS
Platform: Linux
Platform: Windows
Classifier: Development Status :: 3 - Alpha
Classifier: Programming Language :: Python
Classifier: Intended Audience :: Developers
Classifier: Topic :: Scientific/Engineering
Classifier: Operating System :: OS Independent
Requires-Dist: pandas
Requires-Dist: pytest
Requires-Dist: pytest-cov
